agutil/__init__.py
agutil/io/__init__.py
agutil/io/src/__init__.py
agutil/io/src/mplexsocket.py
agutil/io/src/socket.py
agutil/parallel/__init__.py
agutil/parallel/src/__init__.py
agutil/parallel/src/dispatcher.py
agutil/parallel/src/exceptions.py
agutil/parallel/src/parallelize.py
agutil/parallel/src/worker.py
agutil/security/__init__.py
agutil/security/console.py
agutil/security/src/__init__.py
agutil/security/src/cipher.py
agutil/security/src/cipher_header.py
agutil/security/src/connection.py
agutil/security/src/files.py
agutil/security/src/protocols.py
agutil/security/src/securesocket.py
agutil/security/src/server.py
agutil/src/__init__.py
agutil/src/active_timeout.py
agutil/src/args.py
agutil/src/logger.py
agutil/src/misc.py
agutil/src/search_range.py
agutil/src/shell.py
agutil/src/status_bar.py
agutil-5.0.1.dist-info/LICENSE
agutil-5.0.1.dist-info/METADATA
agutil-5.0.1.dist-info/WHEEL
agutil-5.0.1.dist-info/entry_points.txt
agutil-5.0.1.dist-info/top_level.txt
agutil-5.0.1.dist-info/RECORD
