Metadata-Version: 2.1
Name: agutil
Version: 5.0.1
Summary: A collection of python utilities
Home-page: https://gitlab.graubert.com/agraubert/agutil
Author: Aaron Graubert
Author-email: captianjroot@live.com
License: MIT
Keywords: range progress bar loading encryption decryption RSA AES io sockets utilities
Classifier: Development Status :: 5 - Production/Stable
Classifier: Intended Audience :: Developers
Classifier: Topic :: Software Development
Classifier: Topic :: Security :: Cryptography
Classifier: Topic :: Utilities
Classifier: License :: OSI Approved :: MIT License
Classifier: Programming Language :: Python :: 3.4
Classifier: Programming Language :: Python :: 3.5
Classifier: Programming Language :: Python :: 3.6
Classifier: Programming Language :: Python :: 3.7
Classifier: Programming Language :: Python :: 3 :: Only
License-File: LICENSE
Requires-Dist: pycryptodomex (==3.15.0)
Requires-Dist: rsa (==4.9)
